pandaspro/__init__.py
pandaspro/core/__init__.py
pandaspro/core/api.py
pandaspro/core/dates/__init__.py
pandaspro/core/dates/methods.py
pandaspro/core/dates/now.py
pandaspro/core/frame.py
pandaspro/core/pivot.py
pandaspro/core/reshape/__init__.py
pandaspro/core/reshape/tile.py
pandaspro/core/stringfunc.py
pandaspro/core/tools/__init__.py
pandaspro/core/tools/consecgrouper.py
pandaspro/core/tools/corder.py
pandaspro/core/tools/csort.py
pandaspro/core/tools/dfilter.py
pandaspro/core/tools/indate.py
pandaspro/core/tools/inlist.py
pandaspro/core/tools/inrange.py
pandaspro/core/tools/lowervarlist.py
pandaspro/core/tools/pivot.py
pandaspro/core/tools/replace_left_with_right.py
pandaspro/core/tools/search2df.py
pandaspro/core/tools/strpos.py
pandaspro/core/tools/tab.py
pandaspro/core/tools/toolObject.py
pandaspro/core/tools/utils.py
pandaspro/core/tools/varnames.py
pandaspro/cpdbase/__init__.py
pandaspro/cpdbase/api.py
pandaspro/cpdbase/cpd_base_frame.py
pandaspro/cpdbase/design.py
pandaspro/cpdbase/files_version_parser.py
pandaspro/date/__init__.py
pandaspro/date/api.py
pandaspro/date/datepro.py
pandaspro/dev-cpdreport/__init__.py
pandaspro/dev-cpdreport/report.py
pandaspro/email/__init__.py
pandaspro/email/api.py
pandaspro/email/email.py
pandaspro/email/user_template/__init__.py
pandaspro/email/user_template/email_template/__init__.py
pandaspro/email/user_template/email_template/data_distribution.html
pandaspro/email/user_template/email_template/styles.css
pandaspro/email/user_template/engines/__init__.py
pandaspro/email/user_template/engines/data_distribution.py
pandaspro/email/user_template/senders/__init__.py
pandaspro/email/user_template/senders/sender_data_distribution.py
pandaspro/email/utlis.py
pandaspro/io/__init__.py
pandaspro/io/api.py
pandaspro/io/cellpro/__init__.py
pandaspro/io/cellpro/cellpro.py
pandaspro/io/excel/__init__.py
pandaspro/io/excel/_customstyle.py
pandaspro/io/excel/base.py
pandaspro/io/excel/cdformat.py
pandaspro/io/excel/class_example.py
pandaspro-0.10.9.dist-info/METADATA
pandaspro-0.10.9.dist-info/WHEEL
pandaspro-0.10.9.dist-info/RECORD
