Metadata-Version: 2.3
Name: pandaspro
Version: 0.10.9
Summary: Upgraded pandas package for easier dataframe operations
License: MIT
Author: Shiyao Wang
Author-email: sw1016@georgetown.edu
Requires-Python: >=3.8,<3.12
Classifier: License :: OSI Approved :: MIT License
Classifier: Programming Language :: Python :: 3
Classifier: Programming Language :: Python :: 3.8
Classifier: Programming Language :: Python :: 3.9
Classifier: Programming Language :: Python :: 3.10
Classifier: Programming Language :: Python :: 3.11
Requires-Dist: PyPDF2 (>=3.0.1)
Requires-Dist: jinja2 (>=3.1.4)
Requires-Dist: maya (>=0.6.1)
Requires-Dist: numpy (>=1.24)
Requires-Dist: openpyxl (>=3.1.5)
Requires-Dist: pandas (>=2.2.1,<2.3.0)
Requires-Dist: tabulate (>=0.9.0)
Requires-Dist: termcolor (>=2.4.0)
Requires-Dist: xlwings (>=0.31.10)
Project-URL: Homepage, https://github.com/soluentre/pandaspro
